odoo/addons/ebill_postfinance_server_env/README.rst
odoo/addons/ebill_postfinance_server_env/__init__.py
odoo/addons/ebill_postfinance_server_env/__manifest__.py
odoo/addons/ebill_postfinance_server_env/i18n/ebill_postfinance_server_env.pot
odoo/addons/ebill_postfinance_server_env/models/__init__.py
odoo/addons/ebill_postfinance_server_env/models/ebill_postfinance_service.py
odoo/addons/ebill_postfinance_server_env/readme/CONTRIBUTORS.rst
odoo/addons/ebill_postfinance_server_env/readme/DESCRIPTION.rst
odoo/addons/ebill_postfinance_server_env/static/description/icon.png
odoo/addons/ebill_postfinance_server_env/static/description/index.html
odoo14_addon_ebill_postfinance_server_env-14.0.1.0.1.dev2.dist-info/METADATA
odoo14_addon_ebill_postfinance_server_env-14.0.1.0.1.dev2.dist-info/WHEEL
odoo14_addon_ebill_postfinance_server_env-14.0.1.0.1.dev2.dist-info/top_level.txt
odoo14_addon_ebill_postfinance_server_env-14.0.1.0.1.dev2.dist-info/RECORD
